mongodb_finance/__init__.py
mongodb_finance/data_process.py
mongodb_finance-0.0.6.dist-info/LICENSE
mongodb_finance-0.0.6.dist-info/METADATA
mongodb_finance-0.0.6.dist-info/WHEEL
mongodb_finance-0.0.6.dist-info/top_level.txt
mongodb_finance-0.0.6.dist-info/RECORD
