Metadata-Version: 2.1
Name: mongodb-finance
Version: 0.0.6
Summary: A package for mongodb server
Home-page: UNKNOWN
Author: Yonghua Su
Author-email: 13207106053@163.com
License: UNKNOWN
Platform: UNKNOWN
Classifier: Programming Language :: Python :: 3
Classifier: License :: OSI Approved :: MIT License
Classifier: Operating System :: OS Independent
Requires-Python: >=3.6
License-File: LICENSE
Requires-Dist: pymongo
Requires-Dist: pandas
